Metadata-Version: 2.1
Name: csch
Version: 0.0.0
Summary: csch package
Home-page: https://github.com/gregorpatof/csch_package
Author: Olivier Mailhot
License: UNKNOWN
Platform: UNKNOWN
Classifier: Programming Language :: Python :: 3
Classifier: License :: OSI Approved :: MIT License
Classifier: Operating System :: OS Independent
Requires-Python: >=3.6
License-File: LICENSE
